LICENSE
README.md
setup.py
lerobot_teleoperator_fs101_leader/__init__.py
lerobot_teleoperator_fs101_leader/config_fs101_leader.py
lerobot_teleoperator_fs101_leader/fs101_leader.py
lerobot_teleoperator_fs101_leader.egg-info/PKG-INFO
lerobot_teleoperator_fs101_leader.egg-info/SOURCES.txt
lerobot_teleoperator_fs101_leader.egg-info/dependency_links.txt
lerobot_teleoperator_fs101_leader.egg-info/requires.txt
lerobot_teleoperator_fs101_leader.egg-info/top_level.txt