Metadata-Version: 2.4
Name: lerobot_teleoperator_fs101_leader
Version: 0.0.2
Summary: LeRobot teleoperator integration
Author: Welt-liu
Author-email: 1994524450@qq.com
Classifier: Programming Language :: Python :: 3
Classifier: License :: OSI Approved :: Apache Software License
Classifier: Operating System :: OS Independent
Requires-Python: >=3.10
License-File: LICENSE
Requires-Dist: lerobot-motor-starai
Requires-Dist: lerobot
Requires-Dist: fashionstar-uart-sdk>=1.3.6
Dynamic: author
Dynamic: author-email
Dynamic: classifier
Dynamic: license-file
Dynamic: requires-dist
Dynamic: requires-python
Dynamic: summary
